{"name":"build-javascript","namedChunkGroups":{"polyfill":{"name":"polyfill","assets":[{"name":"webpack-runtime-75243b080f712ebeca14.js","size":3780},{"name":"polyfill-820bdfa320e71645ec97.js","size":85018}],"filteredAssets":0,"assetsSize":88798,"filteredAuxiliaryAssets":2,"auxiliaryAssetsSize":226367},"app":{"name":"app","assets":[{"name":"webpack-runtime-75243b080f712ebeca14.js","size":3780},{"name":"framework-34c4775408c4a2a587eb.js","size":140775},{"name":"styles.4a0660e553708fc04e43.css","size":37230},{"name":"app-ce375a2b440cf6fa39af.js","size":196633}],"filteredAssets":0,"assetsSize":378418,"filteredAuxiliaryAssets":3,"auxiliaryAssetsSize":1184735},"component---src-pages-404-tsx":{"name":"component---src-pages-404-tsx","assets":[{"name":"component---src-pages-404-tsx-8b0e5c8b3925c8b5fa58.js","size":810}],"filteredAssets":0,"assetsSize":810,"filteredAuxiliaryAssets":1,"auxiliaryAssetsSize":2009},"component---src-pages-index-tsx":{"name":"component---src-pages-index-tsx","assets":[{"name":"component---src-pages-index-tsx-4cf5bad57d340bc2354f.js","size":1233643}],"filteredAssets":0,"assetsSize":1233643,"filteredAuxiliaryAssets":1,"auxiliaryAssetsSize":4070856}},"assetsByChunkName":{"polyfill":["webpack-runtime-75243b080f712ebeca14.js","polyfill-820bdfa320e71645ec97.js"],"app":["webpack-runtime-75243b080f712ebeca14.js","framework-34c4775408c4a2a587eb.js","styles.4a0660e553708fc04e43.css","app-ce375a2b440cf6fa39af.js"],"component---src-pages-404-tsx":["component---src-pages-404-tsx-8b0e5c8b3925c8b5fa58.js"],"component---src-pages-index-tsx":["component---src-pages-index-tsx-4cf5bad57d340bc2354f.js"]},"childAssetsByChunkName":{}}